verb/__init__.py
verb-0.0.5.dist-info/LICENSE
verb-0.0.5.dist-info/METADATA
verb-0.0.5.dist-info/WHEEL
verb-0.0.5.dist-info/top_level.txt
verb-0.0.5.dist-info/RECORD
