Metadata-Version: 2.1
Name: verb
Version: 0.0.5
Summary: Easy make mini-languages to do python things.
Home-page: https://github.com/i2mint/verb
Author: OtoSense
License: apache-2.0
Keywords: parser,interpreter,programming language,command line
Platform: any
Requires-Dist: lined
